{
    "Limit": 10,
    "Offset": 0,
    "TotalResults": 1,
    "Locale": "en_US",
    "Results": [
        {
            "Id": "1054662050",
            "CID": "755f5126-d9e6-55db-bf54-a6b37efbe4a2",
            "SourceClient": "asda-groceries",
            "LastModeratedTime": "2019-10-16T06:00:08.000+00:00",
            "LastModificationTime": "2019-10-16T06:00:08.000+00:00",
            "ProductId": "910003059636",
            "AuthorId": "6961284559",
            "ContentLocale": "en_GB",
            "IsFeatured": false,
            "InappropriateFeedbackList": [
                {
                    "AuthorId": "zpclzurhbe3vud438i1rewg9gk",
                    "SubmissionTime": "2019-10-16T05:40:55.000+00:00"
                }
            ],
            "TotalInappropriateFeedbackCount": 1,
            "TotalClientResponseCount": 0,
            "TotalCommentCount": 0,
            "Rating": 3,
            "SecondaryRatingsOrder": [
                "Quality",
                "Value"
            ],
            "IsRatingsOnly": false,
            "Helpfulness": 1.0,
            "TotalFeedbackCount": 5,
            "TotalNegativeFeedbackCount": 0,
            "TotalPositiveFeedbackCount": 5,
            "ModerationStatus": "APPROVED",
            "SubmissionId": "l631xto6vif72jad8gf2l4s7i",
            "SubmissionTime": "2019-04-28T11:25:28.000+00:00",
            "ReviewText": "I’ve been eating McVities biscuits for breakfast for years.  Last year they reduced their packet size from 500 to 400g whilst keeping the price the same.  They also changed the recipe slightly which makes the biscuit much more crumbly.  Buying a double pack saves a bit.  I still prefer these biscuits to any other digestives. If you’re happy to pay 20% more than they used to cost, stick with McVities.",
            "Title": "Still the best",
            "UserNickname": "Ruth56",
            "SecondaryRatings": {
                "Quality": {
                    "Value": 4,
                    "Id": "Quality",
                    "Label": "Quality of Product",
                    "DisplayType": "NORMAL",
                    "ValueLabel": null,
                    "MinLabel": null,
                    "ValueRange": 5,
                    "MaxLabel": null
                },
                "Value": {
                    "Value": 3,
                    "Id": "Value",
                    "Label": "Value of Product",
                    "DisplayType": "NORMAL",
                    "ValueLabel": null,
                    "MinLabel": null,
                    "ValueRange": 5,
                    "MaxLabel": null
                }
            },
            "AdditionalFields": {},
            "ContextDataValuesOrder": [],
            "IsSyndicated": false,
            "ProductRecommendationIds": [],
            "Cons": null,
            "Badges": {},
            "AdditionalFieldsOrder": [],
            "BadgesOrder": [],
            "Videos": [],
            "CampaignId": null,
            "ContextDataValues": {},
            "TagDimensionsOrder": [],
            "ClientResponses": [],
            "Photos": [],
            "TagDimensions": {},
            "RatingRange": 5,
            "Pros": null,
            "UserLocation": null,
            "IsRecommended": null,
            "CommentIds": []
        }
    ],
    "Includes": {},
    "HasErrors": false,
    "Errors": []
}